cupi/__init__.py
cupi/callbacks.py
cupi/cli.py
cupi/config.py
cupi/logger.py
cupi/main.py
cupi/run.py
cupi/computer_use_demo/loop.py
cupi/computer_use_demo/tools/__init__.py
cupi/computer_use_demo/tools/base.py
cupi/computer_use_demo/tools/bash.py
cupi/computer_use_demo/tools/collection.py
cupi/computer_use_demo/tools/computer.py
cupi/computer_use_demo/tools/edit.py
cupi/computer_use_demo/tools/run.py
cupi-0.0.2.dist-info/LICENSE
cupi-0.0.2.dist-info/METADATA
cupi-0.0.2.dist-info/WHEEL
cupi-0.0.2.dist-info/entry_points.txt
cupi-0.0.2.dist-info/top_level.txt
cupi-0.0.2.dist-info/RECORD
